magnetron_control/verilog/latch_sr.v
module latch_sr(
	input wire s, r,
	output reg q
);


	always @ (s, r) 
	begin
	
		if(s == 0 && r == 0)
			q <= q;
		
		else if(s == 0 && r == 1)
			q <= 0;
		
		else if(s == 1 && r == 0)
			q <= 1;
		
		else if(s == 1 && r == 1)
			q <= 1'bX;

	end

endmodule

magnetron_control/tests/latch_sr_tb.v
// Code your testbench here
// or browse Examples
`timescale 1ns/1ps
`include "../verilog/latch_sr.v"

module latch_sr_tb();

    reg s_tb,r_tb;
    wire q_tb;
    
    latch_sr UUT(.s(s_tb), .r(r_tb), .q(q_tb));
    
    initial 
        begin
            $dumpfile("latch_sr_tb.vcd");
            $dumpvars(0, latch_sr_tb);

                 r_tb=0; s_tb=0; 
            #10  r_tb=0; s_tb=1; 
            #10  r_tb=1; s_tb=0; 
            #10  r_tb=1; s_tb=1;
            #10  r_tb=0; s_tb=0;  
            #10  r_tb=0; s_tb=1; 
            #10  r_tb=1; s_tb=0;
            #10  r_tb=1; s_tb=1;
            #10  r_tb=0; s_tb=0;
            #10  r_tb=0; s_tb=1;
            #10  r_tb=1; s_tb=0;
            #10  r_tb=1; s_tb=1;
        
            #10;
        end
endmodule

magnetron_control/tests/latch_sr_tb.vcd
$date
	Wed May 11 23:38:17 2022
$end
$version
	Icarus Verilog
$end
$timescale
	1ps
$end
$scope module latch_sr_tb $end
$var wire 1 ! q_tb $end
$var reg 1 " r_tb $end
$var reg 1 # s_tb $end
$scope module UUT $end
$var wire 1 $ r $end
$var wire 1 % s $end
$var reg 1 & q $end
$upscope $end
$upscope $end
$enddefinitions $end
#0
$dumpvars
x&
0%
0$
0#
0"
x!
$end
#10000
1&
1!
1#
1%
#20000
0&
0!
0#
0%
1"
1$
#30000
x&
x!
1#
1%
#40000
0#
0%
0"
0$
#50000
1&
1!
1#
1%
#60000
0&
0!
0#
0%
1"
1$
#70000
x&
x!
1#
1%
#80000
0#
0%
0"
0$
#90000
1&
1!
1#
1%
#100000
0&
0!
0#
0%
1"
1$
#110000
x&
x!
1#
1%
