magnetron_control/verilog/latch_sr.v
module latch_sr(
	input wire s, r,
	output reg q
);


	always @ (s, r) 
	begin
	
		if(s == 0 && r == 0)
			q <= q;
		
		else if(s == 0 && r == 1)
			q <= 0;
		
		else if(s == 1 && r == 0)
			q <= 1;
		
		else if(s == 1 && r == 1)
			q <= 1'bX;

	end

endmodule

magnetron_control/verilog/mag_logic.v
module mag_logic (
    input wire startn , stopn , clearn, door_closed, timer_done, 
    output reg  s, r
);

	 always @(negedge startn, stopn, clearn, door_closed, timer_done) 
	 begin

        if(!clearn || !stopn || timer_done || !door_closed) 
            begin
                s = 0;  
                r = 1; 
            end

        else if(!startn && door_closed) 
            begin                       
                s = 1;    
                r = 0;  
            end

        else 
            begin
                s = 0; 
                r = 1; 
            end
    end

endmodule

magnetron_control/magnetron_controller/magnetron_controller.v
`include "../magnetron_control/magnetron_controller/hdl/latch_sr.v"
`include "../magnetron_control/magnetron_controller/hdl/mag_logic.v"

module magnetron_controller(
    input wire startn , stopn , clearn, door_closed, timer_done, 
    output wire mag_on
); 
    wire r, s;

    mag_logic maglogic (
    	.startn(startn), 
    	.stopn(stopn), 
    	.clearn(clearn), 
    	.door_closed(door_closed_tb),
    	.timer_done(timer_done), 
    	.s(s), .r(r));
    
    latch_sr latchsr (.s(s), .r(r), .q(mag_on));  
    
endmodule

magnetron_control/tests/magnetron_controller_tb.v
`timescale 1ns/1ps
`include "../magnetron_control/magnetron_controller/magnetron_controller.v"


module magnetron_controller_tb();

    reg startn_tb, stopn_tb , clearn_tb, door_closed_tb, timer_done_tb;
    wire mag_on_tb;

    magnetron_controller UUT(
        .startn(startn_tb),
        .stopn(stopn_tb),
        .clearn(clearn_tb),
        .door_closed(door_closed_tb),
        .timer_done(timer_done_tb),
        .mag_on(mag_on_tb));
    
   
    initial begin
        $dumpfile("magnetron_controller_tb.vcd");
		$dumpvars(0,magnetron_controller_tb);

        startn_tb=0; stopn_tb=0; clearn_tb=0; timer_done_tb=1'bx; door_closed_tb=0;   

        #10 startn_tb=1; stopn_tb=1; clearn_tb=0; timer_done_tb=1'bx; door_closed_tb=0;   
        #10 startn_tb=1; stopn_tb=1; clearn_tb=0; timer_done_tb=1'bx; door_closed_tb=1;   
        #10 startn_tb=1; stopn_tb=1; clearn_tb=0; timer_done_tb=1; door_closed_tb=0;   
        #10 startn_tb=1; stopn_tb=1; clearn_tb=0; timer_done_tb=1; door_closed_tb=1;   
        #10 startn_tb=1; stopn_tb=1; clearn_tb=1; timer_done_tb=0; door_closed_tb=0;   
        #10 startn_tb=1; stopn_tb=1; clearn_tb=1; timer_done_tb=0; door_closed_tb=1;   
        #10 startn_tb=1; stopn_tb=1; clearn_tb=1; timer_done_tb=1; door_closed_tb=0;   
        #10 startn_tb=1; stopn_tb=1; clearn_tb=1; timer_done_tb=1; door_closed_tb=1;   

        #10 startn_tb=1; stopn_tb=1; clearn_tb=0; timer_done_tb=0; door_closed_tb=0;   
        #10 startn_tb=1; stopn_tb=1; clearn_tb=0; timer_done_tb=0; door_closed_tb=1;   
        #10 startn_tb=1; stopn_tb=1; clearn_tb=0; timer_done_tb=1; door_closed_tb=0;   
        #10 startn_tb=1; stopn_tb=1; clearn_tb=0; timer_done_tb=1; door_closed_tb=1;   
        #10 startn_tb=1; stopn_tb=1; clearn_tb=1; timer_done_tb=0; door_closed_tb=0;   
        #10 startn_tb=1; stopn_tb=1; clearn_tb=1; timer_done_tb=0; door_closed_tb=1;   
        #10 startn_tb=1; stopn_tb=0; clearn_tb=1; timer_done_tb=0; door_closed_tb=1;   
        #10 startn_tb=1; stopn_tb=0; clearn_tb=1; timer_done_tb=0; door_closed_tb=1;   

        #10 startn_tb=1; stopn_tb=1; clearn_tb=1; timer_done_tb=1; door_closed_tb=0;   
        #10 startn_tb=1; stopn_tb=1; clearn_tb=1; timer_done_tb=1; door_closed_tb=0;   
        #10 startn_tb=1; stopn_tb=1; clearn_tb=1; timer_done_tb=1; door_closed_tb=0;   
        #10 startn_tb=1; stopn_tb=1; clearn_tb=1; timer_done_tb=0; door_closed_tb=0;   
        #10 startn_tb=1; stopn_tb=1; clearn_tb=1; timer_done_tb=0; door_closed_tb=0;   
        #10 startn_tb=1; stopn_tb=0; clearn_tb=1; timer_done_tb=0; door_closed_tb=0;   
        #10 startn_tb=1; stopn_tb=0; clearn_tb=1; timer_done_tb=0; door_closed_tb=0;   
        #10 startn_tb=1; stopn_tb=0; clearn_tb=1; timer_done_tb=0; door_closed_tb=0;   

        #10 startn_tb=0; stopn_tb=1; clearn_tb=1; timer_done_tb=0; door_closed_tb=0;   
        #10 startn_tb=0; stopn_tb=1; clearn_tb=1; timer_done_tb=0; door_closed_tb=1;   
        #10 startn_tb=0; stopn_tb=1; clearn_tb=1; timer_done_tb=1; door_closed_tb=0;   
        #10 startn_tb=0; stopn_tb=1; clearn_tb=1; timer_done_tb=1; door_closed_tb=1;   
        #10 startn_tb=0; stopn_tb=1; clearn_tb=1; timer_done_tb=0; door_closed_tb=0;   
        #10 startn_tb=1; stopn_tb=1; clearn_tb=1; timer_done_tb=0; door_closed_tb=1;   
        #10 startn_tb=1; stopn_tb=1; clearn_tb=1; timer_done_tb=1; door_closed_tb=0;   
        #10 startn_tb=1; stopn_tb=1; clearn_tb=1; timer_done_tb=1; door_closed_tb=1;   

        #10 startn_tb=1; stopn_tb=1; clearn_tb=1; timer_done_tb=0; door_closed_tb=1;   
        #50 startn_tb=0; stopn_tb=1; clearn_tb=1; timer_done_tb=0; door_closed_tb=1;   
        #5 startn_tb=1; stopn_tb=0; clearn_tb=1; timer_done_tb=0; door_closed_tb=1;   
        #50 startn_tb=1; stopn_tb=1; clearn_tb=1; timer_done_tb=1; door_closed_tb=1;   
        #50 startn_tb=1; stopn_tb=0; clearn_tb=1; timer_done_tb=1; door_closed_tb=1;

    end
endmodule

magnetron_control/tests/magnetron_controller_tb.vcd
$date
	Thu May 12 01:42:55 2022
$end
$version
	Icarus Verilog
$end
$timescale
	1ps
$end
$scope module magnetron_controller_tb $end
$var wire 1 ! mag_on_tb $end
$var reg 1 " clearn_tb $end
$var reg 1 # door_closed_tb $end
$var reg 1 $ startn_tb $end
$var reg 1 % stopn_tb $end
$var reg 1 & timer_done_tb $end
$scope module UUT $end
$var wire 1 ' clearn $end
$var wire 1 ( door_closed $end
$var wire 1 ) door_closed_tb $end
$var wire 1 ! mag_on $end
$var wire 1 * r $end
$var wire 1 + s $end
$var wire 1 , startn $end
$var wire 1 - stopn $end
$var wire 1 . timer_done $end
$scope module maglogic $end
$var wire 1 ' clearn $end
$var wire 1 ) door_closed $end
$var wire 1 , startn $end
$var wire 1 - stopn $end
$var wire 1 . timer_done $end
$var reg 1 / r $end
$var reg 1 0 s $end
$upscope $end
$scope module latchsr $end
$var wire 1 * r $end
$var wire 1 + s $end
$var reg 1 1 q $end
$upscope $end
$upscope $end
$upscope $end
$enddefinitions $end
#0
$dumpvars
01
00
1/
x.
0-
0,
0+
1*
z)
0(
0'
x&
0%
0$
0#
0"
0!
$end
#10000
1%
1-
1$
1,
#20000
1#
1(
#30000
0#
0(
1&
1.
#40000
1#
1(
#50000
0#
0(
0&
0.
1"
1'
#60000
1#
1(
#70000
0#
0(
1&
1.
#80000
1#
1(
#90000
0#
0(
0&
0.
0"
0'
#100000
1#
1(
#110000
0#
0(
1&
1.
#120000
1#
1(
#130000
0#
0(
0&
0.
1"
1'
#140000
1#
1(
#150000
0%
0-
#170000
0#
0(
1&
1.
1%
1-
#200000
0&
0.
#220000
0%
0-
#250000
1%
1-
0$
0,
#260000
1#
1(
#270000
0#
0(
1&
1.
#280000
1#
1(
#290000
0#
0(
0&
0.
#300000
1#
1(
1$
1,
#310000
0#
0(
1&
1.
#320000
1#
1(
#330000
0&
0.
#380000
0$
0,
#385000
0%
0-
1$
1,
#435000
1&
1.
1%
1-
#485000
0%
0-
