timer_input_control/encoder/design.sv
module codificador_prioridade(
  output reg [3:0] saida_cod,
  output wire loadn,
  input wire [9:0] teclado_microondas,
  input wire enablen);
  
  assign loadn = (enablen | ~(teclado_microondas[0] | teclado_microondas[1] |teclado_microondas[2]| teclado_microondas[3] |teclado_microondas[4]| teclado_microondas[5] | teclado_microondas[6] | teclado_microondas[7] | teclado_microondas[8] | teclado_microondas[9]));
    
    always @(teclado_microondas)
      begin
        casez (teclado_microondas)
          10'b0000000001 : saida_cod = 4'b0000;
          10'b000000001? : saida_cod = 4'b0001;
          10'b00000001?? : saida_cod = 4'b0010;
          10'b0000001??? : saida_cod = 4'b0011;
          10'b000001???? : saida_cod = 4'b0100;
          10'b00001????? : saida_cod = 4'b0101;
          10'b0001?????? : saida_cod = 4'b0110;
          10'b001??????? : saida_cod = 4'b0111;
          10'b01???????? : saida_cod = 4'b1000;
          10'b1????????? : saida_cod = 4'b1001;
          default: saida_cod = 4'b0000;
        endcase
      end
endmodule

timer_input_control/encoder/testbench.sv
`timescale 1ms/1ms

module encoder_tb;
  
  reg enablen;
  output loadn;
  output [3:0] saida_encoder;
  reg [9:0] numpad;
  
  codificador_prioridade dut(.saida_cod(saida_encoder), .loadn(loadn), .teclado_microondas(numpad), .enablen(enablen));
  
  initial begin
    
    $dumpfile("encoder.vcd");
    $dumpvars(0, encoder_tb);
    
    enablen = 1;  numpad = 10'b0000000010; #10; //enablen ALTO -> loadn ALTO
    numpad = 10'b0000000000; #10;
    enablen = 0;  numpad = 10'b0000000000; #10; //nenhuma tecla pressionada -> loadn ALTO
    
    //pressionando teclas -> loadn BAIXO
    numpad = 10'b0000000001; #10;
    numpad = 10'b0000000010; #10;
    numpad = 10'b0000000100; #10;
    numpad = 10'b0000001001; #10;
    numpad = 10'b0000001000; #10;
    numpad = 10'b0000010000; #10;
    numpad = 10'b0000100000; #10;
    numpad = 10'b0001000000; #10;
    numpad = 10'b0010000000; #10;
    
    

    
  end
  
endmodule

timer_input_control/encoder/encoder.vcd
$date
	Thu May 12 21:39:53 2022
$end
$version
	Icarus Verilog
$end
$timescale
	1ms
$end
$scope module encoder_tb $end
$var wire 1 ! loadn $end
$var wire 4 " saida_encoder [3:0] $end
$var reg 1 # enablen $end
$var reg 10 $ numpad [9:0] $end
$scope module dut $end
$var wire 1 % enablen $end
$var wire 1 ! loadn $end
$var wire 10 & teclado_microondas [9:0] $end
$var reg 4 ' saida_cod [3:0] $end
$upscope $end
$upscope $end
$enddefinitions $end
#0
$dumpvars
b1 '
b10 &
1%
b10 $
1#
b1 "
1!
$end
#10
b0 '
b0 "
b0 $
b0 &
#20
0#
0%
#30
0!
b1 $
b1 &
#40
b1 '
b1 "
b10 $
b10 &
#50
b10 '
b10 "
b100 $
b100 &
#60
b11 '
b11 "
b1001 $
b1001 &
#70
b1000 $
b1000 &
#80
b100 '
b100 "
b10000 $
b10000 &
#90
b101 '
b101 "
b100000 $
b100000 &
#100
b110 '
b110 "
b1000000 $
b1000000 &
#110
b111 '
b111 "
b10000000 $
b10000000 &
