timer_input_control/div_100/design.sv
`timescale 1ms/1ms

//Para dividir a frequencia por 100, usaremos, duas vezes cada, um divisor de frequencia por 5 e outro por 2


module div_5(input clock, output reg clock_div);
  reg [2:0] count = 3'b000; //contandor mod 5
  reg ff_out = 0;
  
  always @(posedge clock)
    begin
      if(count < 4)
        count <= count+1;
      else
        count <= 0;
      clock_div <= ff_out | count[1];
    end
  always @(negedge clock)
    begin
      ff_out <= count[1];
      clock_div <= ff_out | count[1];
    end
  
  
endmodule

module div_2(input clock, output reg clock_div); //divide seguindo a logica de um flip-flop D

  reg Q = 0;
  
  always @(posedge clock)
    begin
      Q <= ~Q;
      clock_div = Q;
    end
  always @(negedge clock)
    begin
      clock_div = Q;
    end
             
endmodule

module div_100(input clock, output wire clock_div);
  
  wire clock_2, clock_4, clock_20;
  
  div_2 D2_1(clock, clock_2);
  div_2 D2_2(clock_2, clock_4);
  div_5 D5_1(clock_4, clock_20);
  div_5 D5_2(clock_20, clock_div);
  
endmodule

timer_input_control/div_100/testbench.sv
`timescale 1ms/1ms

module clock_tb;
  
  reg clock;
  wire clock_div;
  
  div_100 dut(.clock(clock), .clock_div(clock_div));

 	
  always #5 clock <= ~clock; // clock tera uma frequencia de 100hz nesse tb
  
  //o clock de saida devera ter 1hz
  
  initial begin
    
    $dumpfile("div_5.vcd");
    $dumpvars(0, clock_tb);
    
    clock = 0;
    #6000 $finish;
     
  end
  
endmodule

div_100/div_100.vcd
$date
	Thu May 12 21:41:45 2022
$end
$version
	Icarus Verilog
$end
$timescale
	1ms
$end
$scope module clock_tb $end
$var wire 1 ! clock_div $end
$var reg 1 " clock $end
$scope module dut $end
$var wire 1 # clock $end
$var wire 1 $ clock_2 $end
$var wire 1 % clock_20 $end
$var wire 1 & clock_4 $end
$var wire 1 ! clock_div $end
$scope module D2_1 $end
$var wire 1 # clock $end
$var reg 1 ' Q $end
$var reg 1 ( clock_div $end
$upscope $end
$scope module D2_2 $end
$var wire 1 $ clock $end
$var reg 1 ) Q $end
$var reg 1 * clock_div $end
$upscope $end
$scope module D5_1 $end
$var wire 1 & clock $end
$var reg 1 + clock_div $end
$var reg 3 , count [2:0] $end
$var reg 1 - ff_out $end
$upscope $end
$scope module D5_2 $end
$var wire 1 % clock $end
$var reg 1 . clock_div $end
$var reg 3 / count [2:0] $end
$var reg 1 0 ff_out $end
$upscope $end
$upscope $end
$upscope $end
$enddefinitions $end
#0
$dumpvars
00
b0 /
0.
0-
b0 ,
0+
0*
0)
0(
0'
0&
0%
0$
0#
0"
0!
$end
#5
1'
1"
1#
#10
1)
1(
1$
0"
0#
#15
0'
1"
1#
#20
b1 ,
1*
1&
0(
0$
0"
0#
#25
1'
1"
1#
#30
0)
1(
1$
0"
0#
#35
0'
1"
1#
#40
0*
0&
0(
0$
0"
0#
#45
1'
1"
1#
#50
1)
1(
1$
0"
0#
#55
0'
1"
1#
#60
b10 ,
1*
1&
0(
0$
0"
0#
#65
1'
1"
1#
#70
0)
1(
1$
0"
0#
#75
0'
1"
1#
#80
b1 /
1+
1%
1-
0*
0&
0(
0$
0"
0#
#85
1'
1"
1#
#90
1)
1(
1$
0"
0#
#95
0'
1"
1#
#100
b11 ,
1*
1&
0(
0$
0"
0#
#105
1'
1"
1#
#110
0)
1(
1$
0"
0#
#115
0'
1"
1#
#120
0*
0&
0(
0$
0"
0#
#125
1'
1"
1#
#130
1)
1(
1$
0"
0#
#135
0'
1"
1#
#140
b100 ,
1*
1&
0(
0$
0"
0#
#145
1'
1"
1#
#150
0)
1(
1$
0"
0#
#155
0'
1"
1#
#160
0-
0*
0&
0(
0$
0"
0#
#165
1'
1"
1#
#170
1)
1(
1$
0"
0#
#175
0'
1"
1#
#180
0+
0%
b0 ,
1*
1&
0(
0$
0"
0#
#185
1'
1"
1#
#190
0)
1(
1$
0"
0#
#195
0'
1"
1#
#200
0*
0&
0(
0$
0"
0#
#205
1'
1"
1#
#210
1)
1(
1$
0"
0#
#215
0'
1"
1#
#220
b1 ,
1*
1&
0(
0$
0"
0#
#225
1'
1"
1#
#230
0)
1(
1$
0"
0#
#235
0'
1"
1#
#240
0*
0&
0(
0$
0"
0#
#245
1'
1"
1#
#250
1)
1(
1$
0"
0#
#255
0'
1"
1#
#260
b10 ,
1*
1&
0(
0$
0"
0#
#265
1'
1"
1#
#270
0)
1(
1$
0"
0#
#275
0'
1"
1#
#280
b10 /
1+
1%
1-
0*
0&
0(
0$
0"
0#
#285
1'
1"
1#
#290
1)
1(
1$
0"
0#
#295
0'
1"
1#
#300
b11 ,
1*
1&
0(
0$
0"
0#
#305
1'
1"
1#
#310
0)
1(
1$
0"
0#
#315
0'
1"
1#
#320
0*
0&
0(
0$
0"
0#
#325
1'
1"
1#
#330
1)
1(
1$
0"
0#
#335
0'
1"
1#
#340
b100 ,
1*
1&
0(
0$
0"
0#
#345
1'
1"
1#
#350
0)
1(
1$
0"
0#
#355
0'
1"
1#
#360
0-
0*
0&
0(
0$
0"
0#
#365
1'
1"
1#
#370
1)
1(
1$
0"
0#
#375
0'
1"
1#
#380
1.
1!
10
0+
0%
b0 ,
1*
1&
0(
0$
0"
0#
#385
1'
1"
1#
#390
0)
1(
1$
0"
0#
#395
0'
1"
1#
#400
0*
0&
0(
0$
0"
0#
#405
1'
1"
1#
#410
1)
1(
1$
0"
0#
#415
0'
1"
1#
#420
b1 ,
1*
1&
0(
0$
0"
0#
#425
1'
1"
1#
#430
0)
1(
1$
0"
0#
#435
0'
1"
1#
#440
0*
0&
0(
0$
0"
0#
#445
1'
1"
1#
#450
1)
1(
1$
0"
0#
#455
0'
1"
1#
#460
b10 ,
1*
1&
0(
0$
0"
0#
#465
1'
1"
1#
#470
0)
1(
1$
0"
0#
#475
0'
1"
1#
#480
b11 /
1+
1%
1-
0*
0&
0(
0$
0"
0#
#485
1'
1"
1#
#490
1)
1(
1$
0"
0#
#495
0'
1"
1#
#500
b11 ,
1*
1&
0(
0$
0"
0#
#505
1'
1"
1#
#510
0)
1(
1$
0"
0#
#515
0'
1"
1#
#520
0*
0&
0(
0$
0"
0#
#525
1'
1"
1#
#530
1)
1(
1$
0"
0#
#535
0'
1"
1#
#540
b100 ,
1*
1&
0(
0$
0"
0#
#545
1'
1"
1#
#550
0)
1(
1$
0"
0#
#555
0'
1"
1#
#560
0-
0*
0&
0(
0$
0"
0#
#565
1'
1"
1#
#570
1)
1(
1$
0"
0#
#575
0'
1"
1#
#580
0+
0%
b0 ,
1*
1&
0(
0$
0"
0#
#585
1'
1"
1#
#590
0)
1(
1$
0"
0#
#595
0'
1"
1#
#600
0*
0&
0(
0$
0"
0#
#605
1'
1"
1#
#610
1)
1(
1$
0"
0#
#615
0'
1"
1#
#620
b1 ,
1*
1&
0(
0$
0"
0#
#625
1'
1"
1#
#630
0)
1(
1$
0"
0#
#635
0'
1"
1#
#640
0*
0&
0(
0$
0"
0#
#645
1'
1"
1#
#650
1)
1(
1$
0"
0#
#655
0'
1"
1#
#660
b10 ,
1*
1&
0(
0$
0"
0#
#665
1'
1"
1#
#670
0)
1(
1$
0"
0#
#675
0'
1"
1#
#680
b100 /
1+
1%
1-
0*
0&
0(
0$
0"
0#
#685
1'
1"
1#
#690
1)
1(
1$
0"
0#
#695
0'
1"
1#
#700
b11 ,
1*
1&
0(
0$
0"
0#
#705
1'
1"
1#
#710
0)
1(
1$
0"
0#
#715
0'
1"
1#
#720
0*
0&
0(
0$
0"
0#
#725
1'
1"
1#
#730
1)
1(
1$
0"
0#
#735
0'
1"
1#
#740
b100 ,
1*
1&
0(
0$
0"
0#
#745
1'
1"
1#
#750
0)
1(
1$
0"
0#
#755
0'
1"
1#
#760
0-
0*
0&
0(
0$
0"
0#
#765
1'
1"
1#
#770
1)
1(
1$
0"
0#
#775
0'
1"
1#
#780
00
0+
0%
b0 ,
1*
1&
0(
0$
0"
0#
#785
1'
1"
1#
#790
0)
1(
1$
0"
0#
#795
0'
1"
1#
#800
0*
0&
0(
0$
0"
0#
#805
1'
1"
1#
#810
1)
1(
1$
0"
0#
#815
0'
1"
1#
#820
b1 ,
1*
1&
0(
0$
0"
0#
#825
1'
1"
1#
#830
0)
1(
1$
0"
0#
#835
0'
1"
1#
#840
0*
0&
0(
0$
0"
0#
#845
1'
1"
1#
#850
1)
1(
1$
0"
0#
#855
0'
1"
1#
#860
b10 ,
1*
1&
0(
0$
0"
0#
#865
1'
1"
1#
#870
0)
1(
1$
0"
0#
#875
0'
1"
1#
#880
0.
0!
b0 /
1+
1%
1-
0*
0&
0(
0$
0"
0#
#885
1'
1"
1#
#890
1)
1(
1$
0"
0#
#895
0'
1"
1#
#900
b11 ,
1*
1&
0(
0$
0"
0#
#905
1'
1"
1#
#910
0)
1(
1$
0"
0#
#915
0'
1"
1#
#920
0*
0&
0(
0$
0"
0#
#925
1'
1"
1#
#930
1)
1(
1$
0"
0#
#935
0'
1"
1#
#940
b100 ,
1*
1&
0(
0$
0"
0#
#945
1'
1"
1#
#950
0)
1(
1$
0"
0#
#955
0'
1"
1#
#960
0-
0*
0&
0(
0$
0"
0#
#965
1'
1"
1#
#970
1)
1(
1$
0"
0#
#975
0'
1"
1#
#980
0+
0%
b0 ,
1*
1&
0(
0$
0"
0#
#985
1'
1"
1#
#990
0)
1(
1$
0"
0#
#995
0'
1"
1#
#1000
0*
0&
0(
0$
0"
0#
#1005
1'
1"
1#
#1010
1)
1(
1$
0"
0#
#1015
0'
1"
1#
#1020
b1 ,
1*
1&
0(
0$
0"
0#
#1025
1'
1"
1#
#1030
0)
1(
1$
0"
0#
#1035
0'
1"
1#
#1040
0*
0&
0(
0$
0"
0#
#1045
1'
1"
1#
#1050
1)
1(
1$
0"
0#
#1055
0'
1"
1#
#1060
b10 ,
1*
1&
0(
0$
0"
0#
#1065
1'
1"
1#
#1070
0)
1(
1$
0"
0#
#1075
0'
1"
1#
#1080
b1 /
1+
1%
1-
0*
0&
0(
0$
0"
0#
#1085
1'
1"
1#
#1090
1)
1(
1$
0"
0#
#1095
0'
1"
1#
#1100
b11 ,
1*
1&
0(
0$
0"
0#
#1105
1'
1"
1#
#1110
0)
1(
1$
0"
0#
#1115
0'
1"
1#
#1120
0*
0&
0(
0$
0"
0#
#1125
1'
1"
1#
#1130
1)
1(
1$
0"
0#
#1135
0'
1"
1#
#1140
b100 ,
1*
1&
0(
0$
0"
0#
#1145
1'
1"
1#
#1150
0)
1(
1$
0"
0#
#1155
0'
1"
1#
#1160
0-
0*
0&
0(
0$
0"
0#
#1165
1'
1"
1#
#1170
1)
1(
1$
0"
0#
#1175
0'
1"
1#
#1180
0+
0%
b0 ,
1*
1&
0(
0$
0"
0#
#1185
1'
1"
1#
#1190
0)
1(
1$
0"
0#
#1195
0'
1"
1#
#1200
0*
0&
0(
0$
0"
0#
#1205
1'
1"
1#
#1210
1)
1(
1$
0"
0#
#1215
0'
1"
1#
#1220
b1 ,
1*
1&
0(
0$
0"
0#
#1225
1'
1"
1#
#1230
0)
1(
1$
0"
0#
#1235
0'
1"
1#
#1240
0*
0&
0(
0$
0"
0#
#1245
1'
1"
1#
#1250
1)
1(
1$
0"
0#
#1255
0'
1"
1#
#1260
b10 ,
1*
1&
0(
0$
0"
0#
#1265
1'
1"
1#
#1270
0)
1(
1$
0"
0#
#1275
0'
1"
1#
#1280
b10 /
1+
1%
1-
0*
0&
0(
0$
0"
0#
#1285
1'
1"
1#
#1290
1)
1(
1$
0"
0#
#1295
0'
1"
1#
#1300
b11 ,
1*
1&
0(
0$
0"
0#
#1305
1'
1"
1#
#1310
0)
1(
1$
0"
0#
#1315
0'
1"
1#
#1320
0*
0&
0(
0$
0"
0#
#1325
1'
1"
1#
#1330
1)
1(
1$
0"
0#
#1335
0'
1"
1#
#1340
b100 ,
1*
1&
0(
0$
0"
0#
#1345
1'
1"
1#
#1350
0)
1(
1$
0"
0#
#1355
0'
1"
1#
#1360
0-
0*
0&
0(
0$
0"
0#
#1365
1'
1"
1#
#1370
1)
1(
1$
0"
0#
#1375
0'
1"
1#
#1380
1.
1!
10
0+
0%
b0 ,
1*
1&
0(
0$
0"
0#
#1385
1'
1"
1#
#1390
0)
1(
1$
0"
0#
#1395
0'
1"
1#
#1400
0*
0&
0(
0$
0"
0#
#1405
1'
1"
1#
#1410
1)
1(
1$
0"
0#
#1415
0'
1"
1#
#1420
b1 ,
1*
1&
0(
0$
0"
0#
#1425
1'
1"
1#
#1430
0)
1(
1$
0"
0#
#1435
0'
1"
1#
#1440
0*
0&
0(
0$
0"
0#
#1445
1'
1"
1#
#1450
1)
1(
1$
0"
0#
#1455
0'
1"
1#
#1460
b10 ,
1*
1&
0(
0$
0"
0#
#1465
1'
1"
1#
#1470
0)
1(
1$
0"
0#
#1475
0'
1"
1#
#1480
b11 /
1+
1%
1-
0*
0&
0(
0$
0"
0#
#1485
1'
1"
1#
#1490
1)
1(
1$
0"
0#
#1495
0'
1"
1#
#1500
b11 ,
1*
1&
0(
0$
0"
0#
#1505
1'
1"
1#
#1510
0)
1(
1$
0"
0#
#1515
0'
1"
1#
#1520
0*
0&
0(
0$
0"
0#
#1525
1'
1"
1#
#1530
1)
1(
1$
0"
0#
#1535
0'
1"
1#
#1540
b100 ,
1*
1&
0(
0$
0"
0#
#1545
1'
1"
1#
#1550
0)
1(
1$
0"
0#
#1555
0'
1"
1#
#1560
0-
0*
0&
0(
0$
0"
0#
#1565
1'
1"
1#
#1570
1)
1(
1$
0"
0#
#1575
0'
1"
1#
#1580
0+
0%
b0 ,
1*
1&
0(
0$
0"
0#
#1585
1'
1"
1#
#1590
0)
1(
1$
0"
0#
#1595
0'
1"
1#
#1600
0*
0&
0(
0$
0"
0#
#1605
1'
1"
1#
#1610
1)
1(
1$
0"
0#
#1615
0'
1"
1#
#1620
b1 ,
1*
1&
0(
0$
0"
0#
#1625
1'
1"
1#
#1630
0)
1(
1$
0"
0#
#1635
0'
1"
1#
#1640
0*
0&
0(
0$
0"
0#
#1645
1'
1"
1#
#1650
1)
1(
1$
0"
0#
#1655
0'
1"
1#
#1660
b10 ,
1*
1&
0(
0$
0"
0#
#1665
1'
1"
1#
#1670
0)
1(
1$
0"
0#
#1675
0'
1"
1#
#1680
b100 /
1+
1%
1-
0*
0&
0(
0$
0"
0#
#1685
1'
1"
1#
#1690
1)
1(
1$
0"
0#
#1695
0'
1"
1#
#1700
b11 ,
1*
1&
0(
0$
0"
0#
#1705
1'
1"
1#
#1710
0)
1(
1$
0"
0#
#1715
0'
1"
1#
#1720
0*
0&
0(
0$
0"
0#
#1725
1'
1"
1#
#1730
1)
1(
1$
0"
0#
#1735
0'
1"
1#
#1740
b100 ,
1*
1&
0(
0$
0"
0#
#1745
1'
1"
1#
#1750
0)
1(
1$
0"
0#
#1755
0'
1"
1#
#1760
0-
0*
0&
0(
0$
0"
0#
#1765
1'
1"
1#
#1770
1)
1(
1$
0"
0#
#1775
0'
1"
1#
#1780
00
0+
0%
b0 ,
1*
1&
0(
0$
0"
0#
#1785
1'
1"
1#
#1790
0)
1(
1$
0"
0#
#1795
0'
1"
1#
#1800
0*
0&
0(
0$
0"
0#
#1805
1'
1"
1#
#1810
1)
1(
1$
0"
0#
#1815
0'
1"
1#
#1820
b1 ,
1*
1&
0(
0$
0"
0#
#1825
1'
1"
1#
#1830
0)
1(
1$
0"
0#
#1835
0'
1"
1#
#1840
0*
0&
0(
0$
0"
0#
#1845
1'
1"
1#
#1850
1)
1(
1$
0"
0#
#1855
0'
1"
1#
#1860
b10 ,
1*
1&
0(
0$
0"
0#
#1865
1'
1"
1#
#1870
0)
1(
1$
0"
0#
#1875
0'
1"
1#
#1880
0.
0!
b0 /
1+
1%
1-
0*
0&
0(
0$
0"
0#
#1885
1'
1"
1#
#1890
1)
1(
1$
0"
0#
#1895
0'
1"
1#
#1900
b11 ,
1*
1&
0(
0$
0"
0#
#1905
1'
1"
1#
#1910
0)
1(
1$
0"
0#
#1915
0'
1"
1#
#1920
0*
0&
0(
0$
0"
0#
#1925
1'
1"
1#
#1930
1)
1(
1$
0"
0#
#1935
0'
1"
1#
#1940
b100 ,
1*
1&
0(
0$
0"
0#
#1945
1'
1"
1#
#1950
0)
1(
1$
0"
0#
#1955
0'
1"
1#
#1960
0-
0*
0&
0(
0$
0"
0#
#1965
1'
1"
1#
#1970
1)
1(
1$
0"
0#
#1975
0'
1"
1#
#1980
0+
0%
b0 ,
1*
1&
0(
0$
0"
0#
#1985
1'
1"
1#
#1990
0)
1(
1$
0"
0#
#1995
0'
1"
1#
#2000
0*
0&
0(
0$
0"
0#
#2005
1'
1"
1#
#2010
1)
1(
1$
0"
0#
#2015
0'
1"
1#
#2020
b1 ,
1*
1&
0(
0$
0"
0#
#2025
1'
1"
1#
#2030
0)
1(
1$
0"
0#
#2035
0'
1"
1#
#2040
0*
0&
0(
0$
0"
0#
#2045
1'
1"
1#
#2050
1)
1(
1$
0"
0#
#2055
0'
1"
1#
#2060
b10 ,
1*
1&
0(
0$
0"
0#
#2065
1'
1"
1#
#2070
0)
1(
1$
0"
0#
#2075
0'
1"
1#
#2080
b1 /
1+
1%
1-
0*
0&
0(
0$
0"
0#
#2085
1'
1"
1#
#2090
1)
1(
1$
0"
0#
#2095
0'
1"
1#
#2100
b11 ,
1*
1&
0(
0$
0"
0#
#2105
1'
1"
1#
#2110
0)
1(
1$
0"
0#
#2115
0'
1"
1#
#2120
0*
0&
0(
0$
0"
0#
#2125
1'
1"
1#
#2130
1)
1(
1$
0"
0#
#2135
0'
1"
1#
#2140
b100 ,
1*
1&
0(
0$
0"
0#
#2145
1'
1"
1#
#2150
0)
1(
1$
0"
0#
#2155
0'
1"
1#
#2160
0-
0*
0&
0(
0$
0"
0#
#2165
1'
1"
1#
#2170
1)
1(
1$
0"
0#
#2175
0'
1"
1#
#2180
0+
0%
b0 ,
1*
1&
0(
0$
0"
0#
#2185
1'
1"
1#
#2190
0)
1(
1$
0"
0#
#2195
0'
1"
1#
#2200
0*
0&
0(
0$
0"
0#
#2205
1'
1"
1#
#2210
1)
1(
1$
0"
0#
#2215
0'
1"
1#
#2220
b1 ,
1*
1&
0(
0$
0"
0#
#2225
1'
1"
1#
#2230
0)
1(
1$
0"
0#
#2235
0'
1"
1#
#2240
0*
0&
0(
0$
0"
0#
#2245
1'
1"
1#
#2250
1)
1(
1$
0"
0#
#2255
0'
1"
1#
#2260
b10 ,
1*
1&
0(
0$
0"
0#
#2265
1'
1"
1#
#2270
0)
1(
1$
0"
0#
#2275
0'
1"
1#
#2280
b10 /
1+
1%
1-
0*
0&
0(
0$
0"
0#
#2285
1'
1"
1#
#2290
1)
1(
1$
0"
0#
#2295
0'
1"
1#
#2300
b11 ,
1*
1&
0(
0$
0"
0#
#2305
1'
1"
1#
#2310
0)
1(
1$
0"
0#
#2315
0'
1"
1#
#2320
0*
0&
0(
0$
0"
0#
#2325
1'
1"
1#
#2330
1)
1(
1$
0"
0#
#2335
0'
1"
1#
#2340
b100 ,
1*
1&
0(
0$
0"
0#
#2345
1'
1"
1#
#2350
0)
1(
1$
0"
0#
#2355
0'
1"
1#
#2360
0-
0*
0&
0(
0$
0"
0#
#2365
1'
1"
1#
#2370
1)
1(
1$
0"
0#
#2375
0'
1"
1#
#2380
1.
1!
10
0+
0%
b0 ,
1*
1&
0(
0$
0"
0#
#2385
1'
1"
1#
#2390
0)
1(
1$
0"
0#
#2395
0'
1"
1#
#2400
0*
0&
0(
0$
0"
0#
#2405
1'
1"
1#
#2410
1)
1(
1$
0"
0#
#2415
0'
1"
1#
#2420
b1 ,
1*
1&
0(
0$
0"
0#
#2425
1'
1"
1#
#2430
0)
1(
1$
0"
0#
#2435
0'
1"
1#
#2440
0*
0&
0(
0$
0"
0#
#2445
1'
1"
1#
#2450
1)
1(
1$
0"
0#
#2455
0'
1"
1#
#2460
b10 ,
1*
1&
0(
0$
0"
0#
#2465
1'
1"
1#
#2470
0)
1(
1$
0"
0#
#2475
0'
1"
1#
#2480
b11 /
1+
1%
1-
0*
0&
0(
0$
0"
0#
#2485
1'
1"
1#
#2490
1)
1(
1$
0"
0#
#2495
0'
1"
1#
#2500
b11 ,
1*
1&
0(
0$
0"
0#
#2505
1'
1"
1#
#2510
0)
1(
1$
0"
0#
#2515
0'
1"
1#
#2520
0*
0&
0(
0$
0"
0#
#2525
1'
1"
1#
#2530
1)
1(
1$
0"
0#
#2535
0'
1"
1#
#2540
b100 ,
1*
1&
0(
0$
0"
0#
#2545
1'
1"
1#
#2550
0)
1(
1$
0"
0#
#2555
0'
1"
1#
#2560
0-
0*
0&
0(
0$
0"
0#
#2565
1'
1"
1#
#2570
1)
1(
1$
0"
0#
#2575
0'
1"
1#
#2580
0+
0%
b0 ,
1*
1&
0(
0$
0"
0#
#2585
1'
1"
1#
#2590
0)
1(
1$
0"
0#
#2595
0'
1"
1#
#2600
0*
0&
0(
0$
0"
0#
#2605
1'
1"
1#
#2610
1)
1(
1$
0"
0#
#2615
0'
1"
1#
#2620
b1 ,
1*
1&
0(
0$
0"
0#
#2625
1'
1"
1#
#2630
0)
1(
1$
0"
0#
#2635
0'
1"
1#
#2640
0*
0&
0(
0$
0"
0#
#2645
1'
1"
1#
#2650
1)
1(
1$
0"
0#
#2655
0'
1"
1#
#2660
b10 ,
1*
1&
0(
0$
0"
0#
#2665
1'
1"
1#
#2670
0)
1(
1$
0"
0#
#2675
0'
1"
1#
#2680
b100 /
1+
1%
1-
0*
0&
0(
0$
0"
0#
#2685
1'
1"
1#
#2690
1)
1(
1$
0"
0#
#2695
0'
1"
1#
#2700
b11 ,
1*
1&
0(
0$
0"
0#
#2705
1'
1"
1#
#2710
0)
1(
1$
0"
0#
#2715
0'
1"
1#
#2720
0*
0&
0(
0$
0"
0#
#2725
1'
1"
1#
#2730
1)
1(
1$
0"
0#
#2735
0'
1"
1#
#2740
b100 ,
1*
1&
0(
0$
0"
0#
#2745
1'
1"
1#
#2750
0)
1(
1$
0"
0#
#2755
0'
1"
1#
#2760
0-
0*
0&
0(
0$
0"
0#
#2765
1'
1"
1#
#2770
1)
1(
1$
0"
0#
#2775
0'
1"
1#
#2780
00
0+
0%
b0 ,
1*
1&
0(
0$
0"
0#
#2785
1'
1"
1#
#2790
0)
1(
1$
0"
0#
#2795
0'
1"
1#
#2800
0*
0&
0(
0$
0"
0#
#2805
1'
1"
1#
#2810
1)
1(
1$
0"
0#
#2815
0'
1"
1#
#2820
b1 ,
1*
1&
0(
0$
0"
0#
#2825
1'
1"
1#
#2830
0)
1(
1$
0"
0#
#2835
0'
1"
1#
#2840
0*
0&
0(
0$
0"
0#
#2845
1'
1"
1#
#2850
1)
1(
1$
0"
0#
#2855
0'
1"
1#
#2860
b10 ,
1*
1&
0(
0$
0"
0#
#2865
1'
1"
1#
#2870
0)
1(
1$
0"
0#
#2875
0'
1"
1#
#2880
0.
0!
b0 /
1+
1%
1-
0*
0&
0(
0$
0"
0#
#2885
1'
1"
1#
#2890
1)
1(
1$
0"
0#
#2895
0'
1"
1#
#2900
b11 ,
1*
1&
0(
0$
0"
0#
#2905
1'
1"
1#
#2910
0)
1(
1$
0"
0#
#2915
0'
1"
1#
#2920
0*
0&
0(
0$
0"
0#
#2925
1'
1"
1#
#2930
1)
1(
1$
0"
0#
#2935
0'
1"
1#
#2940
b100 ,
1*
1&
0(
0$
0"
0#
#2945
1'
1"
1#
#2950
0)
1(
1$
0"
0#
#2955
0'
1"
1#
#2960
0-
0*
0&
0(
0$
0"
0#
#2965
1'
1"
1#
#2970
1)
1(
1$
0"
0#
#2975
0'
1"
1#
#2980
0+
0%
b0 ,
1*
1&
0(
0$
0"
0#
#2985
1'
1"
1#
#2990
0)
1(
1$
0"
0#
#2995
0'
1"
1#
#3000
0*
0&
0(
0$
0"
0#
#3005
1'
1"
1#
#3010
1)
1(
1$
0"
0#
#3015
0'
1"
1#
#3020
b1 ,
1*
1&
0(
0$
0"
0#
#3025
1'
1"
1#
#3030
0)
1(
1$
0"
0#
#3035
0'
1"
1#
#3040
0*
0&
0(
0$
0"
0#
#3045
1'
1"
1#
#3050
1)
1(
1$
0"
0#
#3055
0'
1"
1#
#3060
b10 ,
1*
1&
0(
0$
0"
0#
#3065
1'
1"
1#
#3070
0)
1(
1$
0"
0#
#3075
0'
1"
1#
#3080
b1 /
1+
1%
1-
0*
0&
0(
0$
0"
0#
#3085
1'
1"
1#
#3090
1)
1(
1$
0"
0#
#3095
0'
1"
1#
#3100
b11 ,
1*
1&
0(
0$
0"
0#
#3105
1'
1"
1#
#3110
0)
1(
1$
0"
0#
#3115
0'
1"
1#
#3120
0*
0&
0(
0$
0"
0#
#3125
1'
1"
1#
#3130
1)
1(
1$
0"
0#
#3135
0'
1"
1#
#3140
b100 ,
1*
1&
0(
0$
0"
0#
#3145
1'
1"
1#
#3150
0)
1(
1$
0"
0#
#3155
0'
1"
1#
#3160
0-
0*
0&
0(
0$
0"
0#
#3165
1'
1"
1#
#3170
1)
1(
1$
0"
0#
#3175
0'
1"
1#
#3180
0+
0%
b0 ,
1*
1&
0(
0$
0"
0#
#3185
1'
1"
1#
#3190
0)
1(
1$
0"
0#
#3195
0'
1"
1#
#3200
0*
0&
0(
0$
0"
0#
#3205
1'
1"
1#
#3210
1)
1(
1$
0"
0#
#3215
0'
1"
1#
#3220
b1 ,
1*
1&
0(
0$
0"
0#
#3225
1'
1"
1#
#3230
0)
1(
1$
0"
0#
#3235
0'
1"
1#
#3240
0*
0&
0(
0$
0"
0#
#3245
1'
1"
1#
#3250
1)
1(
1$
0"
0#
#3255
0'
1"
1#
#3260
b10 ,
1*
1&
0(
0$
0"
0#
#3265
1'
1"
1#
#3270
0)
1(
1$
0"
0#
#3275
0'
1"
1#
#3280
b10 /
1+
1%
1-
0*
0&
0(
0$
0"
0#
#3285
1'
1"
1#
#3290
1)
1(
1$
0"
0#
#3295
0'
1"
1#
#3300
b11 ,
1*
1&
0(
0$
0"
0#
#3305
1'
1"
1#
#3310
0)
1(
1$
0"
0#
#3315
0'
1"
1#
#3320
0*
0&
0(
0$
0"
0#
#3325
1'
1"
1#
#3330
1)
1(
1$
0"
0#
#3335
0'
1"
1#
#3340
b100 ,
1*
1&
0(
0$
0"
0#
#3345
1'
1"
1#
#3350
0)
1(
1$
0"
0#
#3355
0'
1"
1#
#3360
0-
0*
0&
0(
0$
0"
0#
#3365
1'
1"
1#
#3370
1)
1(
1$
0"
0#
#3375
0'
1"
1#
#3380
1.
1!
10
0+
0%
b0 ,
1*
1&
0(
0$
0"
0#
#3385
1'
1"
1#
#3390
0)
1(
1$
0"
0#
#3395
0'
1"
1#
#3400
0*
0&
0(
0$
0"
0#
#3405
1'
1"
1#
#3410
1)
1(
1$
0"
0#
#3415
0'
1"
1#
#3420
b1 ,
1*
1&
0(
0$
0"
0#
#3425
1'
1"
1#
#3430
0)
1(
1$
0"
0#
#3435
0'
1"
1#
#3440
0*
0&
0(
0$
0"
0#
#3445
1'
1"
1#
#3450
1)
1(
1$
0"
0#
#3455
0'
1"
1#
#3460
b10 ,
1*
1&
0(
0$
0"
0#
#3465
1'
1"
1#
#3470
0)
1(
1$
0"
0#
#3475
0'
1"
1#
#3480
b11 /
1+
1%
1-
0*
0&
0(
0$
0"
0#
#3485
1'
1"
1#
#3490
1)
1(
1$
0"
0#
#3495
0'
1"
1#
#3500
b11 ,
1*
1&
0(
0$
0"
0#
#3505
1'
1"
1#
#3510
0)
1(
1$
0"
0#
#3515
0'
1"
1#
#3520
0*
0&
0(
0$
0"
0#
#3525
1'
1"
1#
#3530
1)
1(
1$
0"
0#
#3535
0'
1"
1#
#3540
b100 ,
1*
1&
0(
0$
0"
0#
#3545
1'
1"
1#
#3550
0)
1(
1$
0"
0#
#3555
0'
1"
1#
#3560
0-
0*
0&
0(
0$
0"
0#
#3565
1'
1"
1#
#3570
1)
1(
1$
0"
0#
#3575
0'
1"
1#
#3580
0+
0%
b0 ,
1*
1&
0(
0$
0"
0#
#3585
1'
1"
1#
#3590
0)
1(
1$
0"
0#
#3595
0'
1"
1#
#3600
0*
0&
0(
0$
0"
0#
#3605
1'
1"
1#
#3610
1)
1(
1$
0"
0#
#3615
0'
1"
1#
#3620
b1 ,
1*
1&
0(
0$
0"
0#
#3625
1'
1"
1#
#3630
0)
1(
1$
0"
0#
#3635
0'
1"
1#
#3640
0*
0&
0(
0$
0"
0#
#3645
1'
1"
1#
#3650
1)
1(
1$
0"
0#
#3655
0'
1"
1#
#3660
b10 ,
1*
1&
0(
0$
0"
0#
#3665
1'
1"
1#
#3670
0)
1(
1$
0"
0#
#3675
0'
1"
1#
#3680
b100 /
1+
1%
1-
0*
0&
0(
0$
0"
0#
#3685
1'
1"
1#
#3690
1)
1(
1$
0"
0#
#3695
0'
1"
1#
#3700
b11 ,
1*
1&
0(
0$
0"
0#
#3705
1'
1"
1#
#3710
0)
1(
1$
0"
0#
#3715
0'
1"
1#
#3720
0*
0&
0(
0$
0"
0#
#3725
1'
1"
1#
#3730
1)
1(
1$
0"
0#
#3735
0'
1"
1#
#3740
b100 ,
1*
1&
0(
0$
0"
0#
#3745
1'
1"
1#
#3750
0)
1(
1$
0"
0#
#3755
0'
1"
1#
#3760
0-
0*
0&
0(
0$
0"
0#
#3765
1'
1"
1#
#3770
1)
1(
1$
0"
0#
#3775
0'
1"
1#
#3780
00
0+
0%
b0 ,
1*
1&
0(
0$
0"
0#
#3785
1'
1"
1#
#3790
0)
1(
1$
0"
0#
#3795
0'
1"
1#
#3800
0*
0&
0(
0$
0"
0#
#3805
1'
1"
1#
#3810
1)
1(
1$
0"
0#
#3815
0'
1"
1#
#3820
b1 ,
1*
1&
0(
0$
0"
0#
#3825
1'
1"
1#
#3830
0)
1(
1$
0"
0#
